Metadata-Version: 2.1
Name: scimage
Version: 0.1.7
Summary: Algorithms for data analysis and image processing, including automation of feature extraction and characterization of images.
Home-page: https://github.com/scimage/scimage
Author: Amir Chatraee, Mehrdad Bagheri
Author-email: amirchatraee@yahoo.com, bagheri_mehrdad@hotmail.com
License: GNU GPLv3
Platform: UNKNOWN
Classifier: License :: OSI Approved :: GNU General Public License v3 (GPLv3)
Classifier: Programming Language :: Python :: 3
Classifier: Programming Language :: Python :: 3.8
